dircom.py
dircom-1.0.2.dist-info/licenses/LICENSE
dircom-1.0.2.dist-info/METADATA
dircom-1.0.2.dist-info/WHEEL
dircom-1.0.2.dist-info/entry_points.txt
dircom-1.0.2.dist-info/top_level.txt
dircom-1.0.2.dist-info/RECORD
