Metadata-Version: 2.4
Name: dircom
Version: 1.0.2
Summary: CLI to list serial (COM/USB) ports on Windows, Linux & macOS
Home-page: https://github.com/ncamilo/dircom
Author: Nelson Almeida
Author-email: ncamilo.so@gmail.com
Classifier: Programming Language :: Python :: 3
Classifier: License :: OSI Approved :: GNU General Public License v3 (GPLv3)
Classifier: Operating System :: OS Independent
Requires-Python: >=3.6
License-File: LICENSE
Requires-Dist: pyserial>=3.5
Dynamic: author
Dynamic: author-email
Dynamic: classifier
Dynamic: description
Dynamic: description-content-type
Dynamic: home-page
Dynamic: license-file
Dynamic: requires-dist
Dynamic: requires-python
Dynamic: summary
